oiml_core/__init__.py
oiml_core/ast.py
oiml_core/parser.py
oiml_core-0.1.0.dist-info/LICENSE
oiml_core-0.1.0.dist-info/METADATA
oiml_core-0.1.0.dist-info/WHEEL
oiml_core-0.1.0.dist-info/top_level.txt
oiml_core-0.1.0.dist-info/RECORD
