Metadata-Version: 2.1
Name: oiml-core
Version: 0.1.0
Summary: Parser for OpenIndented Markup Language
Author-email: Zetian Lin <bctnry@outlook.com>
Project-URL: Homepage, https://github.com/bctnry/oiml-core-py
Project-URL: Bug Tracker, https://github.com/bctnry/oiml-core-py/issues
Classifier: Programming Language :: Python :: 3
Classifier: License :: OSI Approved :: MIT License
Classifier: Operating System :: OS Independent
Requires-Python: >=3.7
License-File: LICENSE
